td4/__init__.py
td4/cpu.py
td4/emulate.py
td4/opcode.py
td4/output.py
td4/parse.py
td4-1.0.2.dist-info/LICENSE
td4-1.0.2.dist-info/METADATA
td4-1.0.2.dist-info/WHEEL
td4-1.0.2.dist-info/entry_points.txt
td4-1.0.2.dist-info/RECORD
