Metadata-Version: 2.1
Name: td4
Version: 1.0.2
Summary: 4bit CPU emulator
License: MIT
Author: kota
Author-email: 52403688+yashikota@users.noreply.github.com
Requires-Python: >=3.8,<4.0
Classifier: License :: OSI Approved :: MIT License
Classifier: Programming Language :: Python :: 3
Classifier: Programming Language :: Python :: 3.8
Classifier: Programming Language :: Python :: 3.9
Classifier: Programming Language :: Python :: 3.10
Classifier: Programming Language :: Python :: 3.11
